test_of_time-0.0.2.data/scripts/tot_dev_setup.py
tot/__init__.py
tot/_version.py
tot/benchmark.py
tot/dataset.py
tot/experiment.py
tot/metrics.py
tot/models.py
tot/utils.py
test_of_time-0.0.2.dist-info/METADATA
test_of_time-0.0.2.dist-info/WHEEL
test_of_time-0.0.2.dist-info/top_level.txt
test_of_time-0.0.2.dist-info/RECORD
