Metadata-Version: 2.1
Name: test-of-time
Version: 0.0.2
Summary: Evaluate forecasting models
Home-page: https://github.com/ourownstory/test-of-time
Author: Oskar Triebe
Author-email: trieb@stanford.edu
License: MIT
Platform: UNKNOWN
Classifier: Development Status :: 3 - Alpha
Classifier: License :: OSI Approved :: MIT License
Classifier: Programming Language :: Python :: 3
Classifier: Programming Language :: Python :: 3.6
Classifier: Programming Language :: Python :: 3.7
Classifier: Programming Language :: Python :: 3.8
Classifier: Programming Language :: Python :: 3.9
Classifier: Programming Language :: Python :: 3.10
Classifier: Natural Language :: English
Classifier: Operating System :: OS Independent
Classifier: Operating System :: POSIX :: Linux
Classifier: Operating System :: MacOS :: MacOS X
Classifier: Operating System :: Microsoft :: Windows
Requires-Python: >=3.6
Requires-Dist: neuralprophet (>=0.3.2)
Requires-Dist: numpy (>=1.15.4)
Requires-Dist: pandas (>=1.0.4)
Requires-Dist: dataclasses (>=0.6) ; python_version < "3.7"
Provides-Extra: dev
Requires-Dist: black ; extra == 'dev'
Requires-Dist: prophet ; extra == 'dev'
Requires-Dist: pytest-cov ; extra == 'dev'
Requires-Dist: pytest (>=6.2.3) ; extra == 'dev'
Requires-Dist: sphinx (>=4.2.0) ; extra == 'dev'
Requires-Dist: twine ; extra == 'dev'
Requires-Dist: wheel ; extra == 'dev'
Provides-Extra: full
Requires-Dist: prophet ; extra == 'full'
